maphrs/__init__.py
maphrs/eletronics/__init__.py
maphrs/eletronics/basic.py
maphrs/objects/__init__.py
maphrs/objects/eletronics.py
maphrs/statistics/__init__.py
maphrs/statistics/descriptive.py
maphrs/statistics/uncertainty.py
maphrs-0.0.4.dist-info/METADATA
maphrs-0.0.4.dist-info/WHEEL
maphrs-0.0.4.dist-info/entry_points.txt
maphrs-0.0.4.dist-info/RECORD
